{
  "$type": "Comindware.Platform.Contracts.DatasetModel, Comindware.Platform.Contracts",
  "GlobalAlias": {
    "$type": "Comindware.Platform.Contracts.GlobalAlias, Comindware.Platform.Contracts",
    "Type": "Dataset",
    "Owner": "ProcessingWorkItem",
    "Alias": "newList"
  },
  "IsLazyLoading": false,
  "Name": "Мои задачи ",
  "Columns": {
    "$type": "System.Collections.Generic.List`1[[Comindware.Platform.Contracts.ColumnConfigurationModel, Comindware.Platform.Contracts]], mscorlib",
    "$values": [
      {
        "$type": "Comindware.Platform.Contracts.ColumnConfigurationModel, Comindware.Platform.Contracts",
        "PropertyPath": {
          "$type": "Comindware.Platform.Contracts.GlobalAlias[], Comindware.Platform.Contracts",
          "$values": [
            {
              "$type": "Comindware.Platform.Contracts.GlobalAlias, Comindware.Platform.Contracts",
              "Type": "Attribute",
              "Alias": "title"
            }
          ]
        },
        "Name": "Заголовок",
        "Layout": {
          "$type": "Comindware.Platform.Contracts.ColumnLayoutModel, Comindware.Platform.Contracts",
          "Flex": 1.0,
          "Width": 775.7847290039062
        },
        "IsHidden": false
      },
      {
        "$type": "Comindware.Platform.Contracts.ColumnConfigurationModel, Comindware.Platform.Contracts",
        "PropertyPath": {
          "$type": "Comindware.Platform.Contracts.GlobalAlias[], Comindware.Platform.Contracts",
          "$values": [
            {
              "$type": "Comindware.Platform.Contracts.GlobalAlias, Comindware.Platform.Contracts",
              "Type": "Attribute",
              "Alias": "creationDate"
            }
          ]
        },
        "Name": "Дата создания",
        "Layout": {
          "$type": "Comindware.Platform.Contracts.ColumnLayoutModel, Comindware.Platform.Contracts",
          "Flex": 1.0,
          "Width": 134.78472900390625
        },
        "IsHidden": false
      },
      {
        "$type": "Comindware.Platform.Contracts.ColumnConfigurationModel, Comindware.Platform.Contracts",
        "PropertyPath": {
          "$type": "Comindware.Platform.Contracts.GlobalAlias[], Comindware.Platform.Contracts",
          "$values": [
            {
              "$type": "Comindware.Platform.Contracts.GlobalAlias, Comindware.Platform.Contracts",
              "Type": "Attribute",
              "Alias": "taskStatus"
            }
          ]
        },
        "Name": "Состояние задачи",
        "Layout": {
          "$type": "Comindware.Platform.Contracts.ColumnLayoutModel, Comindware.Platform.Contracts",
          "Flex": 1.0,
          "Width": 142.39236450195312
        },
        "IsHidden": false
      },
      {
        "$type": "Comindware.Platform.Contracts.ColumnConfigurationModel, Comindware.Platform.Contracts",
        "PropertyPath": {
          "$type": "Comindware.Platform.Contracts.GlobalAlias[], Comindware.Platform.Contracts",
          "$values": [
            {
              "$type": "Comindware.Platform.Contracts.GlobalAlias, Comindware.Platform.Contracts",
              "Type": "Attribute",
              "Alias": "cmw.task.objectId"
            },
            {
              "$type": "Comindware.Platform.Contracts.GlobalAlias, Comindware.Platform.Contracts",
              "Type": "Attribute",
              "Owner": "Workitem",
              "Alias": "PlannedStartDate"
            }
          ]
        },
        "Name": "План.дата нач.работы",
        "Layout": {
          "$type": "Comindware.Platform.Contracts.ColumnLayoutModel, Comindware.Platform.Contracts",
          "Flex": 1.0,
          "Width": 168.86458587646484
        },
        "IsHidden": false
      },
      {
        "$type": "Comindware.Platform.Contracts.ColumnConfigurationModel, Comindware.Platform.Contracts",
        "PropertyPath": {
          "$type": "Comindware.Platform.Contracts.GlobalAlias[], Comindware.Platform.Contracts",
          "$values": [
            {
              "$type": "Comindware.Platform.Contracts.GlobalAlias, Comindware.Platform.Contracts",
              "Type": "Attribute",
              "Alias": "cmw.task.objectId"
            },
            {
              "$type": "Comindware.Platform.Contracts.GlobalAlias, Comindware.Platform.Contracts",
              "Type": "Attribute",
              "Owner": "Workitem",
              "Alias": "PlannedEndDate"
            }
          ]
        },
        "Name": "План.дата зав.работы",
        "Layout": {
          "$type": "Comindware.Platform.Contracts.ColumnLayoutModel, Comindware.Platform.Contracts",
          "Flex": 1.0,
          "Width": 165.55209350585938
        },
        "IsHidden": false
      },
      {
        "$type": "Comindware.Platform.Contracts.ColumnConfigurationModel, Comindware.Platform.Contracts",
        "PropertyPath": {
          "$type": "Comindware.Platform.Contracts.GlobalAlias[], Comindware.Platform.Contracts",
          "$values": [
            {
              "$type": "Comindware.Platform.Contracts.GlobalAlias, Comindware.Platform.Contracts",
              "Type": "Attribute",
              "Alias": "cmw.task.objectId"
            },
            {
              "$type": "Comindware.Platform.Contracts.GlobalAlias, Comindware.Platform.Contracts",
              "Type": "Attribute",
              "Owner": "Workitem",
              "Alias": "Status"
            }
          ]
        },
        "Name": "Статус работы",
        "Layout": {
          "$type": "Comindware.Platform.Contracts.ColumnLayoutModel, Comindware.Platform.Contracts",
          "Flex": 1.0,
          "Width": 0.0
        },
        "IsHidden": false
      }
    ]
  },
  "Paging": {
    "$type": "Comindware.Platform.Contracts.PagingConfigurationModel, Comindware.Platform.Contracts",
    "Page": 0,
    "Size": 25
  },
  "Sorting": {
    "$type": "Comindware.Platform.Contracts.SortingConfigurationModel, Comindware.Platform.Contracts",
    "PropertyPath": {
      "$type": "Comindware.Platform.Contracts.GlobalAlias[], Comindware.Platform.Contracts",
      "$values": [
        {
          "$type": "Comindware.Platform.Contracts.GlobalAlias, Comindware.Platform.Contracts",
          "Type": "Attribute",
          "Alias": "taskStatus"
        }
      ]
    },
    "Direction": "Asc",
    "NullValuesOnTop": false
  },
  "ViewType": "General",
  "Filter": {
    "$type": "Comindware.Platform.Contracts.FilterBaseModel, Comindware.Platform.Contracts",
    "Type": "FilterLeaf",
    "PropertyPath": {
      "$type": "Comindware.Platform.Contracts.GlobalAlias[], Comindware.Platform.Contracts",
      "$values": [
        {
          "$type": "Comindware.Platform.Contracts.GlobalAlias, Comindware.Platform.Contracts",
          "Type": "Attribute",
          "Alias": "taskStatus"
        }
      ]
    },
    "Value": "cmw.taskStatus.inProgress",
    "Operator": "eq",
    "DataFormat": "Undefined",
    "GroupOperator": "and"
  },
  "SystemFilterExpression": "@prefix xsd: <http://www.w3.org/2001/XMLSchema#>.\r\n@prefix log: <http://www.w3.org/2000/10/swap/log#>.\r\n@prefix cmw:  <http://comindware.com/logics#>.\r\n{\r\ncmw:securityContext cmw:currentUser ?currentUser.\r\n?item a cmw:UserTask.\r\n    or\r\n    {\r\n       ?item cmw:assignee ?currentUser.\r\n    }\r\n    or\r\n    {\r\n       ?item cmw:possibleAssignee ?currentUser.\r\n    }.\r\n}",
  "SourcePrototype": "cmw.UserTask"
}